__init__.py
exceptions.py
helpers.py
types.py
api/__init__.py
api/app.py
api/dependencies.py
api/flags_router.py
api/models.py
cli/__init__.py
cli/fake_data.py
clients/__init__.py
clients/mongo_db_client.py
domain/__init__.py
domain/flag.py
repo/__init__.py
repo/base.py
repo/doc_store.py
repo/fake_repo.py
services/__init__.py
services/flagship.py
pyflagship-0.1.0.dist-info/METADATA
pyflagship-0.1.0.dist-info/WHEEL
pyflagship-0.1.0.dist-info/top_level.txt
pyflagship-0.1.0.dist-info/RECORD
